reerelease/__about__.py
reerelease/__init__.py
reerelease/config.py
reerelease/errors.py
reerelease/reerelease.py
reerelease/cli/console.py
reerelease/cli/error_codes.py
reerelease/cli/commands/context.py
reerelease/cli/commands/milestone.py
reerelease/cli/commands/problem.py
reerelease/cli/commands/task.py
reerelease/core/context.py
reerelease/core/logging.py
reerelease/core/milestone.py
reerelease/core/task.py
reerelease/service/context_manager.py
reerelease/service/milestone_manager.py
reerelease/service/template_manager.py
reerelease/service/dsl/__init__.py
reerelease/service/dsl/inplace_edit.py
reerelease/service/dsl/memory_manager.py
reerelease/service/dsl/phase1_specs.py
reerelease/service/dsl/phase2_parser.py
reerelease/service/dsl/phase3_renderer.py
reerelease/service/dsl/phase4_validator.py
reerelease/service/dsl/pipeline.py
reerelease/templates/common/file_links.j2
reerelease/templates/context/readme.md.j2
reerelease/templates/context/release.md.j2
reerelease/templates/context/roadmap.md.j2
reerelease/templates/milestone/milestone_section.j2
reerelease/validators/validate_context.py
reerelease/validators/validate_dsl.py
reerelease/validators/validate_milestone.py
reerelease-0.3.1.dist-info/METADATA
reerelease-0.3.1.dist-info/WHEEL
reerelease-0.3.1.dist-info/entry_points.txt
reerelease-0.3.1.dist-info/RECORD
