Metadata-Version: 2.4
Name: reerelease
Version: 0.3.1
Project-URL: Documentation, https://gitlab.com/real-ee/tool/reerelease#readme
Project-URL: Issues, https://gitlab.com/real-ee/tool/reerelease/-/issues
Project-URL: Source, https://gitlab.com/real-ee/tool/reerelease#
Author-email: Laurence DV <laurencedv@realee.tech>
License-Expression: MIT
Classifier: Development Status :: 3 - Alpha
Classifier: Environment :: Console
Classifier: Intended Audience :: Developers
Classifier: Intended Audience :: System Administrators
Classifier: License :: OSI Approved :: MIT License
Classifier: Operating System :: OS Independent
Classifier: Programming Language :: Python
Classifier: Programming Language :: Python :: 3.10
Classifier: Programming Language :: Python :: Implementation :: CPython
Classifier: Topic :: Software Development :: Code Generators
Classifier: Topic :: Software Development :: Documentation
Classifier: Topic :: Text Processing :: Markup :: Markdown
Classifier: Topic :: Utilities
Requires-Python: >=3.10
Requires-Dist: anytree>=2.13.0
Requires-Dist: jinja2>=3.1.6
Requires-Dist: markdown-it-py>=4.0.0
Requires-Dist: questionary>=2.1.1
Requires-Dist: rich>=14.1.0
Requires-Dist: typer>=0.17.4
